intellectronica/__init__.py
intellectronica/ai.py
intellectronica-0.1.202407111800.dist-info/LICENSE
intellectronica-0.1.202407111800.dist-info/METADATA
intellectronica-0.1.202407111800.dist-info/WHEEL
intellectronica-0.1.202407111800.dist-info/top_level.txt
intellectronica-0.1.202407111800.dist-info/RECORD
